google_tui/__init__.py
google_tui/__main__.py
google_tui/cli.py
google_tui/core.py
google_tui-0.1.0.dist-info/LICENSE
google_tui-0.1.0.dist-info/METADATA
google_tui-0.1.0.dist-info/WHEEL
google_tui-0.1.0.dist-info/entry_points.txt
google_tui-0.1.0.dist-info/top_level.txt
google_tui-0.1.0.dist-info/RECORD
